setup.py
lib/argproc/__init__.py
lib/argproc/error.py
lib/argproc/parser.py
lib/argproc/parser_lex.py
lib/argproc/parser_tab.py
lib/argproc/plyparse.py
lib/argproc/processor.py
lib/argproc.egg-info/PKG-INFO
lib/argproc.egg-info/SOURCES.txt
lib/argproc.egg-info/dependency_links.txt
lib/argproc.egg-info/requires.txt
lib/argproc.egg-info/top_level.txt
lib/argproc/test/__init__.py
lib/argproc/test/test_processor.py