Metadata-Version: 1.0
Name: argproc
Version: 1.4
Summary: A rule-based arguments processor
Home-page: http://bitbucket.org/geertj/argproc
Author: Geert Jansen
Author-email: geert@boskant.nl
License: MIT
Platform: UNKNOWN
Classifier: Development Status :: 4 - Beta
Classifier: Environment :: Web Environment
Classifier: Intended Audience :: Developers
Classifier: License :: OSI Approved :: MIT License
Classifier: Operating System :: OS Independent
Classifier: Programming Language :: Python
Classifier: Topic :: Software Development :: Libraries :: Python Modules
